cdxsummary/__init__.py
cdxsummary/__main__.py
cdxsummary/analyzer.py
cdxsummary/parser.py
cdxsummary/sampler.py
cdxsummary/summarizer.py
cdxsummary-0.1.1b5.dist-info/LICENSE
cdxsummary-0.1.1b5.dist-info/METADATA
cdxsummary-0.1.1b5.dist-info/WHEEL
cdxsummary-0.1.1b5.dist-info/entry_points.txt
cdxsummary-0.1.1b5.dist-info/top_level.txt
cdxsummary-0.1.1b5.dist-info/zip-safe
cdxsummary-0.1.1b5.dist-info/RECORD
