Metadata-Version: 2.1
Name: cdxsummary
Version: 0.1.1b5
Summary: Summarize web archive capture index (CDX) files
Home-page: https://github.com/internetarchive/cdx-summary
Author: Sawood Alam
Author-email: sawood@archive.org
License: UNKNOWN
Platform: UNKNOWN
Classifier: Programming Language :: Python :: 3
Classifier: License :: OSI Approved :: GNU Affero General Public License v3
Classifier: Operating System :: OS Independent
Classifier: Topic :: System :: Archiving
Classifier: Topic :: Internet :: WWW/HTTP
Classifier: Topic :: Internet :: WWW/HTTP :: Indexing/Search
Provides: cdxsummary
Requires-Python: >=3.6
License-File: LICENSE
Requires-Dist: internetarchive
Requires-Dist: humanize
Requires-Dist: requests
Requires-Dist: rich
